uniswap_sdk/__init__.py
uniswap_sdk/_cli.py
uniswap_sdk/main.py
uniswap_sdk/packages.py
uniswap_sdk/permit2-manifest.json
uniswap_sdk/permit2.py
uniswap_sdk/py.typed
uniswap_sdk/solver.py
uniswap_sdk/types.py
uniswap_sdk/unirouter-manifest.json
uniswap_sdk/universal_router.py
uniswap_sdk/utils.py
uniswap_sdk/v2-manifest.json
uniswap_sdk/v2.py
uniswap_sdk/v3-manifest.json
uniswap_sdk/v3.py
uniswap_sdk/version.py
uniswap_sdk-0.3.2.dist-info/licenses/LICENSE
uniswap_sdk-0.3.2.dist-info/METADATA
uniswap_sdk-0.3.2.dist-info/WHEEL
uniswap_sdk-0.3.2.dist-info/entry_points.txt
uniswap_sdk-0.3.2.dist-info/top_level.txt
uniswap_sdk-0.3.2.dist-info/RECORD
