Metadata-Version: 2.4
Name: uniswap-sdk
Version: 0.3.2
Summary: uniswap-sdk: SDK for Uniswap smart contracts
Home-page: https://github.com/ApeWorX/uniswap-sdk
Author: ApeWorX Ltd.
Author-email: admin@apeworx.io
License: Apache-2.0
Keywords: ethereum
Classifier: Development Status :: 4 - Beta
Classifier: Intended Audience :: Developers
Classifier: License :: OSI Approved :: Apache Software License
Classifier: Natural Language :: English
Classifier: Operating System :: MacOS
Classifier: Operating System :: POSIX
Classifier: Programming Language :: Python :: 3
Classifier: Programming Language :: Python :: 3.10
Classifier: Programming Language :: Python :: 3.11
Classifier: Programming Language :: Python :: 3.12
Classifier: Programming Language :: Python :: 3.13
Requires-Python: >=3.10,<4
License-File: LICENSE
Requires-Dist: eth-ape<1,>=0.8.43
Requires-Dist: eip712>=0.3
Requires-Dist: networkx<4,>=3.4.2
Requires-Dist: ape-tokens<1,>=0.8.5
Provides-Extra: test
Requires-Dist: pytest; extra == "test"
Requires-Dist: pytest-xdist; extra == "test"
Requires-Dist: pytest-cov; extra == "test"
Requires-Dist: hypothesis; extra == "test"
Provides-Extra: lint
Requires-Dist: black; extra == "lint"
Requires-Dist: mypy; extra == "lint"
Requires-Dist: flake8; extra == "lint"
Requires-Dist: isort; extra == "lint"
Provides-Extra: release
Requires-Dist: setuptools>=75.6.0; extra == "release"
Requires-Dist: wheel; extra == "release"
Requires-Dist: twine; extra == "release"
Provides-Extra: dev
Requires-Dist: pytest; extra == "dev"
Requires-Dist: pytest-xdist; extra == "dev"
Requires-Dist: pytest-cov; extra == "dev"
Requires-Dist: hypothesis; extra == "dev"
Requires-Dist: black; extra == "dev"
Requires-Dist: mypy; extra == "dev"
Requires-Dist: flake8; extra == "dev"
Requires-Dist: isort; extra == "dev"
Requires-Dist: setuptools>=75.6.0; extra == "dev"
Requires-Dist: wheel; extra == "dev"
Requires-Dist: twine; extra == "dev"
Requires-Dist: silverback>=0.7.22; extra == "dev"
Requires-Dist: commitizen; extra == "dev"
Requires-Dist: pre-commit; extra == "dev"
Requires-Dist: pytest-watch; extra == "dev"
Requires-Dist: IPython; extra == "dev"
Requires-Dist: ipdb; extra == "dev"
Provides-Extra: bot
Requires-Dist: silverback>=0.7.22; extra == "bot"
Dynamic: author
Dynamic: author-email
Dynamic: classifier
Dynamic: description
Dynamic: description-content-type
Dynamic: home-page
Dynamic: keywords
Dynamic: license
Dynamic: license-file
Dynamic: provides-extra
Dynamic: requires-dist
Dynamic: requires-python
Dynamic: summary
